LICENSE.rst
MANIFEST.in
README.rst
setup.py
src/node/__init__.py
src/node.ext.xml.egg-info/PKG-INFO
src/node.ext.xml.egg-info/SOURCES.txt
src/node.ext.xml.egg-info/dependency_links.txt
src/node.ext.xml.egg-info/entry_points.txt
src/node.ext.xml.egg-info/namespace_packages.txt
src/node.ext.xml.egg-info/not-zip-safe
src/node.ext.xml.egg-info/requires.txt
src/node.ext.xml.egg-info/top_level.txt
src/node/ext/__init__.py
src/node/ext/xml/__init__.py
src/node/ext/xml/_api.py
src/node/ext/xml/_api.rst
src/node/ext/xml/configure.zcml
src/node/ext/xml/interfaces.py
src/node/ext/xml/tests.py
src/node/ext/xml/testing/__init__.py
src/node/ext/xml/testing/data/new.xml
src/node/ext/xml/testing/data/test.xml
src/node/ext/xml/testing/data/testout.xml